README.rst
setup.py
exercice_math/__init__.py
exercice_math/exercice_math.py
exercice_math.egg-info/PKG-INFO
exercice_math.egg-info/SOURCES.txt
exercice_math.egg-info/dependency_links.txt
exercice_math.egg-info/entry_points.txt
exercice_math.egg-info/top_level.txt