Metadata-Version: 1.0
Name: exercice-math
Version: 0.1
Summary: Exercise de Mathematiques
Home-page: http://
Author: Sebatien Delisle
Author-email: seb0del@gmail.com
License: GNU GPL v3.0 License
Keywords: math training
Platform: UNKNOWN
